MANIFEST.in
README.md
pyproject.toml
setup.py
isosplit5/__init__.py
isosplit5.egg-info/PKG-INFO
isosplit5.egg-info/SOURCES.txt
isosplit5.egg-info/dependency_links.txt
isosplit5.egg-info/requires.txt
isosplit5.egg-info/top_level.txt
src/isocut5.cpp
src/isocut5.h
src/isocut6.cpp
src/isocut6.h
src/isosplit5.cpp
src/isosplit5.h
src/isosplit5_pybind11.cpp
src/isosplit6.cpp
src/isosplit6.h
src/isosplit6_pybind11.cpp
src/jisotonic5.cpp
src/jisotonic5.h
src/ndarray.h