Metadata-Version: 2.1
Name: isosplit5
Version: 0.2.3
Summary: Efficient clustering algorithm for unknown number of unimodal clusters
Author-email: Jeremy Magland <jmagland@flatironinstitute.org>
Project-URL: Homepage, https://github.com/magland/isosplit5_python
Requires-Dist: numpy
Requires-Dist: pybind11>=2.2
